transitleastsquares/JAA546A14limb1-4.csv
transitleastsquares/__init__.py
transitleastsquares/catalog.py
transitleastsquares/command_line.py
transitleastsquares/core.py
transitleastsquares/fap.csv
transitleastsquares/grid.py
transitleastsquares/helpers.py
transitleastsquares/interpolation.py
transitleastsquares/ld_claret_tess.csv
transitleastsquares/main.py
transitleastsquares/results.py
transitleastsquares/stats.py
transitleastsquares/tls_constants.py
transitleastsquares/transit.py
transitleastsquares/validate.py
transitleastsquares/version.py
transitleastsquares-1.0.31.dist-info/LICENSE
transitleastsquares-1.0.31.dist-info/METADATA
transitleastsquares-1.0.31.dist-info/WHEEL
transitleastsquares-1.0.31.dist-info/entry_points.txt
transitleastsquares-1.0.31.dist-info/top_level.txt
transitleastsquares-1.0.31.dist-info/RECORD
