Metadata-Version: 2.1
Name: transitleastsquares
Version: 1.0.31
Summary: An optimized transit-fitting algorithm to search for periodic transits of small planets
Home-page: https://github.com/hippke/tls
Author: Michael Hippke
Author-email: michael@hippke.org
License: MIT
Platform: UNKNOWN
License-File: LICENSE
Requires-Dist: astroquery (>=0.3.9)
Requires-Dist: numpy
Requires-Dist: numba
Requires-Dist: tqdm
Requires-Dist: batman-package
Requires-Dist: configparser
Requires-Dist: argparse ; python_version < "2.7"
Requires-Dist: astropy (<3) ; python_version < "3"
